cjy_wfy6/__init__.py
cjy_wfy6/background.jpg
cjy_wfy6/crash.wav
cjy_wfy6/font.ttf
cjy_wfy6/kaiti.ttf
cjy_wfy6/main.py
cjy_wfy6/racecar.jpg
cjy_wfy6/racestart.wav
cjy_wfy6/tiantiande.wav
cjy_wfy6/photos/1.jpg
cjy_wfy6/photos/10.jpg
cjy_wfy6/photos/11.jpg
cjy_wfy6/photos/12.jpg
cjy_wfy6/photos/13.jpg
cjy_wfy6/photos/14.jpg
cjy_wfy6/photos/15.jpg
cjy_wfy6/photos/2.jpg
cjy_wfy6/photos/3.jpg
cjy_wfy6/photos/4.jpg
cjy_wfy6/photos/5.jpg
cjy_wfy6/photos/6.jpg
cjy_wfy6/photos/7.jpg
cjy_wfy6/photos/70.jpg
cjy_wfy6/photos/8.jpg
cjy_wfy6/photos/9.jpg
cjy_wfy6-0.0.1.dist-info/LICENSE
cjy_wfy6-0.0.1.dist-info/METADATA
cjy_wfy6-0.0.1.dist-info/WHEEL
cjy_wfy6-0.0.1.dist-info/top_level.txt
cjy_wfy6-0.0.1.dist-info/RECORD
